cached_auth/__init__.py
cached_auth/models.py
django_cached_authentication_middleware-0.2.2.dist-info/DESCRIPTION.rst
django_cached_authentication_middleware-0.2.2.dist-info/METADATA
django_cached_authentication_middleware-0.2.2.dist-info/RECORD
django_cached_authentication_middleware-0.2.2.dist-info/WHEEL
django_cached_authentication_middleware-0.2.2.dist-info/metadata.json
django_cached_authentication_middleware-0.2.2.dist-info/top_level.txt
